phanotate-1.6.7.data/scripts/phanotate.py
phanotate_modules/__init__.py
phanotate_modules/edges.py
phanotate_modules/feature.py
phanotate_modules/file.py
phanotate_modules/file_handling.py
phanotate_modules/functions.py
phanotate_modules/gc_frame_plot.py
phanotate_modules/graphs.py
phanotate_modules/locus.py
phanotate_modules/nodes.py
phanotate_modules/orfs.py
phanotate-1.6.7.dist-info/LICENSE
phanotate-1.6.7.dist-info/METADATA
phanotate-1.6.7.dist-info/WHEEL
phanotate-1.6.7.dist-info/top_level.txt
phanotate-1.6.7.dist-info/RECORD
