Metadata-Version: 2.1
Name: phanotate
Version: 1.6.7
Summary: A a tool to annotate phage genomes
Home-page: https://github.com/deprekate/phanotate
Author: Katelyn McNair
Author-email: deprekate@gmail.com
Classifier: Programming Language :: Python :: 3
Classifier: License :: OSI Approved :: GNU General Public License v3 or later (GPLv3+)
Classifier: Operating System :: OS Independent
Requires-Python: >3.5.2
License-File: LICENSE
Requires-Dist: fastpath>=1.3
Requires-Dist: genbank>=0.119
